logs_operations/__init__.py
logs_operations/logger_setup.py
luke_logger-0.2.0.dist-info/LICENSE
luke_logger-0.2.0.dist-info/METADATA
luke_logger-0.2.0.dist-info/WHEEL
luke_logger-0.2.0.dist-info/top_level.txt
luke_logger-0.2.0.dist-info/RECORD
