Metadata-Version: 2.2
Name: luke-logger
Version: 0.2.0
Summary: A logger setup module for Python projects now with support for bugsnag intergration.
Home-page: https://github.com/prakhar-luke-dev/my_logger.git
Author: Prakhar Bhandari
Author-email: prakhar.luke.dev@gmail.com
License: Apache License 2.0
Classifier: Programming Language :: Python :: 3
Classifier: License :: OSI Approved :: Apache Software License
Classifier: Operating System :: OS Independent
Requires-Python: >=3.7
License-File: LICENSE
